.travis.yml
AUTHORS.rst
CHANGELOG.rst
CHANGES.txt
CONTRIBUTING.rst
LICENSE
MANIFEST.in
README.md
README.rst
appveyor.yml
setup.cfg
setup.py
bin/git_sync
docs/authors.rst
docs/changelog.rst
docs/conf.py
docs/contributing.rst
docs/index.rst
docs/installation.rst
docs/readme.rst
docs/requirements.txt
docs/spelling_wordlist.txt
docs/usage.rst
docs/reference/GitSync.rst
docs/reference/index.rst
src/GitSync.egg-info/PKG-INFO
src/GitSync.egg-info/SOURCES.txt
src/GitSync.egg-info/dependency_links.txt
src/GitSync.egg-info/not-zip-safe
src/GitSync.egg-info/requires.txt
src/GitSync.egg-info/top_level.txt
src/gitsync/GitSync.py
src/gitsync/__init__.py
src/gitsync/__main__.py