Metadata-Version: 1.1
Name: GitSync
Version: 0.2
Summary: Use git to sync a project directory on an OS X client with a remote server.
Home-page: https://github.com/clockwork/GitSync
Author: Jachin Rupe
Author-email: jachin@clockwork.net
License: MIT
Platform: UNKNOWN
Classifier: Intended Audience :: Developers
Classifier: Environment :: MacOS X
Classifier: Development Status :: 4 - Beta
Classifier: License :: OSI Approved :: MIT License
Classifier: Natural Language :: English
Classifier: Topic :: Communications :: File Sharing
Classifier: Topic :: Utilities
